social_auth_fastapi-0.1.6.dist-info/METADATA
social_auth_fastapi-0.1.6.dist-info/WHEEL
social_auth_fastapi/__init__.py
social_auth_fastapi/base/__init__.py
social_auth_fastapi/base/database.py
social_auth_fastapi/base/error_codes.py
social_auth_fastapi/base/errors.py
social_auth_fastapi/conf.py
social_auth_fastapi/cruds/__init__.py
social_auth_fastapi/cruds/base.py
social_auth_fastapi/cruds/crud_model_base.py
social_auth_fastapi/cruds/crud_social_account.py
social_auth_fastapi/models/__init__.py
social_auth_fastapi/models/base.py
social_auth_fastapi/models/helper.py
social_auth_fastapi/models/t_social_account.py
social_auth_fastapi/oauth/__init__.py
social_auth_fastapi/oauth/base.py
social_auth_fastapi/oauth/common.py
social_auth_fastapi/oauth/errors.py
social_auth_fastapi/oauth/jwt.py
social_auth_fastapi/oauth/parameters.py
social_auth_fastapi/oauth/signals.py
social_auth_fastapi/oauth/timezone.py
social_auth_fastapi/oauth/tokens.py
social_auth_fastapi/oauth/utils.py
social_auth_fastapi/oauth/web_application.py
social_auth_fastapi/routers/__init__.py
social_auth_fastapi/routers/auth.py
social_auth_fastapi/routers/social.py
social_auth_fastapi/routers/user.py
social_auth_fastapi/schemas/__init__.py
social_auth_fastapi/schemas/auth.py
social_auth_fastapi/schemas/response_schema.py
social_auth_fastapi/schemas/social_account.py
social_auth_fastapi/schemas/token.py
social_auth_fastapi/schemas/user.py
social_auth_fastapi/services/__init__.py
social_auth_fastapi/services/auth.py
social_auth_fastapi/services/social.py
social_auth_fastapi/services/user.py
social_auth_fastapi/social/__init__.py
social_auth_fastapi/social/services/__init__.py
social_auth_fastapi/social/services/facebook.py
social_auth_fastapi/social/services/fitbit.py
social_auth_fastapi/social/services/github.py
social_auth_fastapi/social/services/gitlab.py
social_auth_fastapi/social/services/google.py
social_auth_fastapi/social/services/line.py
social_auth_fastapi/social/services/linkedin.py
social_auth_fastapi/social/services/notion.py
social_auth_fastapi/social/services/twitter.py
social_auth_fastapi-0.1.6.dist-info/RECORD
