Metadata-Version: 2.1
Name: social-auth-fastapi
Version: 0.1.6
Summary: Default template for PDM package
Author-Email: congpc <congpc1305@gmail.com>
Requires-Python: >=3.11
Requires-Dist: fastapi[all]==0.111.0
Requires-Dist: httpx>=0.27.0
Requires-Dist: passlib==1.7.4
Requires-Dist: python-jose>=3.3.0
Requires-Dist: uvicorn[standard]==0.29.0
Requires-Dist: asgiref>=3.8.1
Requires-Dist: asyncpg>=0.29.0
Requires-Dist: python-dateutil>=2.9.0.post0
Requires-Dist: loguru>=0.7.2
Requires-Dist: sqlmodel>=0.0.18
Requires-Dist: requests>=2.32.3
